dry_foundation/__init__.py
dry_foundation/_version.py
dry_foundation/factory.py
dry_foundation/utils.py
dry_foundation/cli/console.py
dry_foundation/cli/interface.py
dry_foundation/cli/launcher.py
dry_foundation/cli/modes.py
dry_foundation/config/__init__.py
dry_foundation/config/default_settings.py
dry_foundation/config/settings.py
dry_foundation/database/__init__.py
dry_foundation/database/handler.py
dry_foundation/database/interface.py
dry_foundation/database/models.py
dry_foundation/database/schema.py
dry_foundation/database/utils.py
dry_foundation/forms/__init__.py
dry_foundation/forms/base.py
dry_foundation/testing/__init__.py
dry_foundation/testing/base.py
dry_foundation/testing/helpers/__init__.py
dry_foundation/testing/helpers/database.py
dry_foundation/testing/helpers/routes.py
dry_foundation-1.6.1.dist-info/METADATA
dry_foundation-1.6.1.dist-info/WHEEL
dry_foundation-1.6.1.dist-info/entry_points.txt
dry_foundation-1.6.1.dist-info/licenses/COPYING
dry_foundation-1.6.1.dist-info/licenses/LICENSE
dry_foundation-1.6.1.dist-info/RECORD
