Metadata-Version: 2.4
Name: dry-foundation
Version: 1.6.1
Summary: Tools and components for building customized and consistent small-scale Flask applications.
Project-URL: Download, https://pypi.org/project/dry-foundation/
Project-URL: Homepage, https://github.com/mitchnegus/DRY-Foundation
Project-URL: Repository, https://github.com/mitchnegus/DRY-Foundation
Project-URL: Changelog, https://github.com/mitchnegus/DRY-Foundation/blob/main/docs/source/CHANGELOG.md
Author-email: Mitch Negus <mitchnegus57@gmail.com>
License: GNU GPLv3
License-File: COPYING
License-File: LICENSE
Classifier: Development Status :: 3 - Alpha
Classifier: Framework :: Flask
Classifier: Framework :: Pytest
Classifier: License :: OSI Approved :: GNU General Public License v3 (GPLv3)
Classifier: Natural Language :: English
Classifier: Operating System :: OS Independent
Classifier: Programming Language :: Python
Requires-Python: >=3.10
Requires-Dist: beautifulsoup4>=4.14.2
Requires-Dist: click<8.3,>=8.2.0
Requires-Dist: flask-wtf==1.2.2
Requires-Dist: flask>=2.2.2
Requires-Dist: gunicorn>=23.0.0
Requires-Dist: pytest>=8.4.1
Requires-Dist: sqlalchemy-views>=0.3.2
Requires-Dist: sqlalchemy>=2.0.0
Provides-Extra: dev
Requires-Dist: coverage==7.13.1; extra == 'dev'
Requires-Dist: furo; extra == 'dev'
Requires-Dist: myst-parser; extra == 'dev'
Requires-Dist: nox~=2025.11.12; extra == 'dev'
Requires-Dist: sphinx; extra == 'dev'
Provides-Extra: docs
Requires-Dist: furo; extra == 'docs'
Requires-Dist: myst-parser; extra == 'docs'
Requires-Dist: sphinx; extra == 'docs'
Provides-Extra: test
Requires-Dist: coverage==7.13.1; extra == 'test'
